README.txt
bootstrap.py
buildout.cfg
ffmpeg.cfg
setup.cfg
setup.py
collective/__init__.py
collective.transcode.daemon.egg-info/PKG-INFO
collective.transcode.daemon.egg-info/SOURCES.txt
collective.transcode.daemon.egg-info/dependency_links.txt
collective.transcode.daemon.egg-info/entry_points.txt
collective.transcode.daemon.egg-info/not-zip-safe
collective.transcode.daemon.egg-info/requires.txt
collective.transcode.daemon.egg-info/top_level.txt
collective/transcode/__init__.py
collective/transcode/daemon/__init__.py
collective/transcode/daemon/config.py
collective/transcode/daemon/crypto.py
collective/transcode/daemon/scheduler.py
collective/transcode/daemon/tests.py
collective/transcode/daemon/transcodedaemon.py
collective/transcode/daemon/xmlrpc.py
docs/CHANGES.txt
docs/CONTRIBUTORS.txt
docs/LICENSE.GPL
docs/LICENSE.txt
scripts/jpeg
scripts/mp4-high
scripts/mp4-low
scripts/webm-high
scripts/webm-low