Metadata-Version: 1.0
Name: collective.transcode.daemon
Version: 0.12
Summary: Video transcoding daemon
Home-page: https://github.com/plumi/collective.transcode.daemon
Author: unweb.me
Author-email: we@unweb.me
License: GPL
Keywords: video transcoding flv mp4 ogg plone zope twisted
Platform: UNKNOWN
Classifier: Framework :: Twisted
Classifier: Intended Audience :: Developers
Classifier: Programming Language :: Python
Classifier: Topic :: Software Development :: Libraries :: Python Modules
Classifier: Topic :: Multimedia :: Video :: Conversion
Classifier: License :: OSI Approved :: GNU General Public License (GPL)
